{
 "updated": "2026-07-01",
 "n_sims": 10000,
 "conditioned_on_results": true,
 "champion": {
  "España": 0.2402,
  "Argentina": 0.1731,
  "Brasil": 0.1313,
  "Francia": 0.1278,
  "Alemania": 0.0652,
  "Inglaterra": 0.0554,
  "Portugal": 0.0382,
  "Países Bajos": 0.0304,
  "México": 0.0244,
  "Bélgica": 0.0233,
  "Colombia": 0.0185,
  "Japón": 0.0137,
  "Marruecos": 0.0094,
  "Canadá": 0.0077,
  "Croacia": 0.0076,
  "Uruguay": 0.0071,
  "Noruega": 0.0052,
  "Suiza": 0.005,
  "Ecuador": 0.004,
  "Senegal": 0.0027,
  "Paraguay": 0.0023,
  "Turquía": 0.0016,
  "Austria": 0.0015,
  "Irán": 0.0008,
  "Corea del Sur": 0.0006,
  "Estados Unidos": 0.0006,
  "Egipto": 0.0006,
  "Costa de Marfil": 0.0003,
  "RD Congo": 0.0003,
  "Australia": 0.0003,
  "Cabo Verde": 0.0002,
  "Argelia": 0.0002,
  "Suecia": 0.0002,
  "Bosnia": 0.0001,
  "Escocia": 0.0001,
  "Ghana": 0.0001
 },
 "reach": {
  "R32": {
   "México": 1.0,
   "Bosnia": 1.0,
   "Sudáfrica": 1.0,
   "Canadá": 1.0,
   "Brasil": 1.0,
   "Marruecos": 1.0,
   "Alemania": 1.0,
   "Egipto": 1.0,
   "Suiza": 1.0,
   "Francia": 1.0,
   "Ghana": 1.0,
   "Estados Unidos": 1.0,
   "Argentina": 1.0,
   "Colombia": 1.0,
   "Países Bajos": 1.0,
   "Portugal": 1.0,
   "España": 1.0,
   "Inglaterra": 1.0,
   "Noruega": 1.0,
   "Croacia": 0.9745,
   "Costa de Marfil": 0.9579,
   "Corea del Sur": 0.9523,
   "Austria": 0.9369,
   "Bélgica": 0.916,
   "Japón": 0.9122,
   "Suecia": 0.8145,
   "Australia": 0.7987,
   "Paraguay": 0.7573,
   "Argelia": 0.6822,
   "Irán": 0.6485,
   "Senegal": 0.6336,
   "Cabo Verde": 0.6158,
   "Escocia": 0.4208,
   "Arabia Saudita": 0.3845,
   "RD Congo": 0.3586,
   "Uruguay": 0.3359,
   "Turquía": 0.2809,
   "Ecuador": 0.2792,
   "Curazao": 0.11,
   "Nueva Zelanda": 0.0839,
   "Túnez": 0.059,
   "Uzbekistán": 0.0378,
   "Jordania": 0.024,
   "Irak": 0.0194,
   "Panamá": 0.0056
  },
  "R16": {
   "España": 0.8878,
   "Brasil": 0.8607,
   "Canadá": 0.8333,
   "Alemania": 0.8165,
   "Países Bajos": 0.7499,
   "Francia": 0.734,
   "México": 0.7024,
   "Argentina": 0.702,
   "Bélgica": 0.6822,
   "Marruecos": 0.6366,
   "Inglaterra": 0.6307,
   "Suiza": 0.6299,
   "Japón": 0.6064,
   "Portugal": 0.5184,
   "Colombia": 0.5184,
   "Estados Unidos": 0.5042,
   "Egipto": 0.4149,
   "Noruega": 0.3737,
   "Croacia": 0.3407,
   "Corea del Sur": 0.3363,
   "Irán": 0.3227,
   "Paraguay": 0.308,
   "Senegal": 0.2953,
   "Costa de Marfil": 0.2945,
   "Austria": 0.2894,
   "Suecia": 0.2581,
   "Australia": 0.2474,
   "Uruguay": 0.2193,
   "Argelia": 0.1792,
   "Sudáfrica": 0.1667,
   "Bosnia": 0.149,
   "Turquía": 0.1447,
   "Cabo Verde": 0.1332,
   "Ghana": 0.1289,
   "Ecuador": 0.1224,
   "Arabia Saudita": 0.0794,
   "Escocia": 0.0623,
   "RD Congo": 0.0581,
   "Nueva Zelanda": 0.0256,
   "Túnez": 0.0132,
   "Curazao": 0.0122,
   "Jordania": 0.0041,
   "Uzbekistán": 0.0035,
   "Irak": 0.0021,
   "Panamá": 0.0017
  },
  "QF": {
   "Brasil": 0.6636,
   "España": 0.6405,
   "Argentina": 0.608,
   "Francia": 0.5607,
   "Alemania": 0.5575,
   "Bélgica": 0.4753,
   "México": 0.4664,
   "Países Bajos": 0.3994,
   "Portugal": 0.3547,
   "Canadá": 0.3538,
   "Colombia": 0.3209,
   "Inglaterra": 0.3162,
   "Japón": 0.2654,
   "Marruecos": 0.1992,
   "Suiza": 0.1771,
   "Croacia": 0.1686,
   "Egipto": 0.1395,
   "Noruega": 0.1325,
   "Irán": 0.1089,
   "Austria": 0.1058,
   "Uruguay": 0.1037,
   "Senegal": 0.1005,
   "Paraguay": 0.0931,
   "Corea del Sur": 0.0791,
   "Estados Unidos": 0.078,
   "Ecuador": 0.0704,
   "Costa de Marfil": 0.0687,
   "Suecia": 0.0616,
   "Argelia": 0.0574,
   "Turquía": 0.0533,
   "Australia": 0.0476,
   "Bosnia": 0.0346,
   "Cabo Verde": 0.0277,
   "Ghana": 0.0266,
   "Sudáfrica": 0.0251,
   "Arabia Saudita": 0.02,
   "RD Congo": 0.017,
   "Escocia": 0.0104,
   "Nueva Zelanda": 0.0052,
   "Túnez": 0.0025,
   "Curazao": 0.0014,
   "Jordania": 0.0011,
   "Panamá": 0.0004,
   "Irak": 0.0003,
   "Uzbekistán": 0.0003
  },
  "SF": {
   "España": 0.4907,
   "Brasil": 0.4836,
   "Argentina": 0.4035,
   "Alemania": 0.3671,
   "Francia": 0.3246,
   "Bélgica": 0.2173,
   "Inglaterra": 0.2,
   "México": 0.1862,
   "Países Bajos": 0.166,
   "Portugal": 0.1543,
   "Japón": 0.1307,
   "Colombia": 0.1174,
   "Canadá": 0.1093,
   "Marruecos": 0.1004,
   "Croacia": 0.0636,
   "Uruguay": 0.0494,
   "Noruega": 0.0493,
   "Suiza": 0.0487,
   "Paraguay": 0.0358,
   "Egipto": 0.0349,
   "Ecuador": 0.0341,
   "Senegal": 0.0315,
   "Irán": 0.0267,
   "Austria": 0.0258,
   "Costa de Marfil": 0.0225,
   "Turquía": 0.0205,
   "Corea del Sur": 0.0203,
   "Estados Unidos": 0.0194,
   "Australia": 0.0136,
   "Suecia": 0.0136,
   "Argelia": 0.0134,
   "Bosnia": 0.006,
   "Ghana": 0.0048,
   "Cabo Verde": 0.0042,
   "Arabia Saudita": 0.0036,
   "RD Congo": 0.0028,
   "Sudáfrica": 0.0017,
   "Escocia": 0.0017,
   "Nueva Zelanda": 0.0003,
   "Jordania": 0.0002,
   "Panamá": 0.0002,
   "Túnez": 0.0001,
   "Curazao": 0.0001,
   "Uzbekistán": 0.0001
  },
  "F": {
   "España": 0.3211,
   "Brasil": 0.3208,
   "Argentina": 0.2433,
   "Alemania": 0.1902,
   "Francia": 0.1855,
   "Bélgica": 0.0949,
   "Inglaterra": 0.0915,
   "México": 0.0854,
   "Países Bajos": 0.0737,
   "Portugal": 0.0665,
   "Japón": 0.051,
   "Canadá": 0.0417,
   "Colombia": 0.0393,
   "Marruecos": 0.0384,
   "Croacia": 0.0234,
   "Uruguay": 0.0193,
   "Ecuador": 0.0146,
   "Noruega": 0.0135,
   "Paraguay": 0.0133,
   "Suiza": 0.0125,
   "Senegal": 0.0096,
   "Egipto": 0.0077,
   "Irán": 0.0061,
   "Austria": 0.0055,
   "Turquía": 0.0052,
   "Costa de Marfil": 0.0049,
   "Estados Unidos": 0.0039,
   "Corea del Sur": 0.0038,
   "Argelia": 0.0032,
   "Suecia": 0.003,
   "Australia": 0.003,
   "Bosnia": 0.0012,
   "Ghana": 0.0009,
   "Cabo Verde": 0.0006,
   "RD Congo": 0.0006,
   "Sudáfrica": 0.0004,
   "Escocia": 0.0003,
   "Arabia Saudita": 0.0002
  }
 },
 "slots": {
  "R32-0": {
   "in": {
    "México": 1.0,
    "RD Congo": 0.2223,
    "Egipto": 0.1623,
    "Bosnia": 0.1355,
    "Ecuador": 0.1262,
    "Ghana": 0.1239,
    "Japón": 0.0775,
    "Suecia": 0.0605
   },
   "advance": {
    "México": 0.7024,
    "Ecuador": 0.0617,
    "RD Congo": 0.0426,
    "Egipto": 0.0405,
    "Japón": 0.0393,
    "España": 0.0386,
    "Bosnia": 0.0219,
    "Ghana": 0.0173
   }
  },
  "R32-1": {
   "in": {
    "Sudáfrica": 1.0,
    "Canadá": 1.0
   },
   "advance": {
    "Canadá": 0.8333,
    "Sudáfrica": 0.1667
   }
  },
  "R32-2": {
   "in": {
    "Brasil": 1.0,
    "Bosnia": 0.3258,
    "Ghana": 0.2094,
    "RD Congo": 0.0958,
    "Egipto": 0.0838,
    "Ecuador": 0.0704,
    "Suecia": 0.0598,
    "Croacia": 0.0578
   },
   "advance": {
    "Brasil": 0.8607,
    "Bosnia": 0.0326,
    "Ecuador": 0.0205,
    "Ghana": 0.0197,
    "Croacia": 0.0173,
    "Japón": 0.0113,
    "Egipto": 0.0105,
    "RD Congo": 0.009
   }
  },
  "R32-3": {
   "in": {
    "Marruecos": 1.0,
    "Australia": 0.525,
    "Paraguay": 0.4518,
    "Estados Unidos": 0.0232
   },
   "advance": {
    "Marruecos": 0.6366,
    "Paraguay": 0.1881,
    "Australia": 0.1665,
    "Estados Unidos": 0.0088
   }
  },
  "R32-4": {
   "in": {
    "Alemania": 0.9957,
    "Bosnia": 0.3337,
    "Ghana": 0.1999,
    "Argelia": 0.0591,
    "Paraguay": 0.0569,
    "Croacia": 0.0543,
    "Egipto": 0.0351,
    "Suecia": 0.0297
   },
   "advance": {
    "Alemania": 0.8136,
    "Bosnia": 0.0414,
    "Ghana": 0.0228,
    "Croacia": 0.0214,
    "Paraguay": 0.0144,
    "Argelia": 0.0127,
    "Senegal": 0.0086,
    "Ecuador": 0.0083
   }
  },
  "R32-5": {
   "in": {
    "Costa de Marfil": 0.8618,
    "Japón": 0.5535,
    "Países Bajos": 0.2451,
    "Suecia": 0.199,
    "Curazao": 0.0796,
    "Ecuador": 0.0543,
    "Alemania": 0.0043,
    "Túnez": 0.0024
   },
   "advance": {
    "Japón": 0.3969,
    "Costa de Marfil": 0.2663,
    "Países Bajos": 0.1922,
    "Suecia": 0.103,
    "Ecuador": 0.029,
    "Curazao": 0.009,
    "Alemania": 0.0029,
    "Túnez": 0.0007
   }
  },
  "R32-6": {
   "in": {
    "Egipto": 0.545,
    "Irán": 0.2996,
    "Bélgica": 0.2596,
    "Bosnia": 0.1616,
    "Ghana": 0.132,
    "Corea del Sur": 0.0875,
    "Paraguay": 0.0865,
    "Argelia": 0.0856
   },
   "advance": {
    "Egipto": 0.2524,
    "Bélgica": 0.1932,
    "Irán": 0.1502,
    "Senegal": 0.0539,
    "Paraguay": 0.0497,
    "Corea del Sur": 0.0472,
    "Bosnia": 0.0453,
    "Argelia": 0.0424
   }
  },
  "R32-7": {
   "in": {
    "Bélgica": 0.5823,
    "Cabo Verde": 0.5187,
    "Arabia Saudita": 0.3305,
    "Irán": 0.195,
    "Egipto": 0.1644,
    "España": 0.0936,
    "Nueva Zelanda": 0.0583,
    "Uruguay": 0.0572
   },
   "advance": {
    "Bélgica": 0.4482,
    "Irán": 0.1253,
    "Cabo Verde": 0.1124,
    "Egipto": 0.1027,
    "España": 0.0806,
    "Arabia Saudita": 0.0715,
    "Uruguay": 0.0372,
    "Nueva Zelanda": 0.0221
   }
  },
  "R32-8": {
   "in": {
    "Suiza": 1.0,
    "Corea del Sur": 0.2077,
    "Senegal": 0.1282,
    "Irán": 0.0673,
    "Argelia": 0.061,
    "Turquía": 0.06,
    "Paraguay": 0.0582,
    "Suecia": 0.0568
   },
   "advance": {
    "Suiza": 0.6299,
    "Corea del Sur": 0.0684,
    "Senegal": 0.0656,
    "Turquía": 0.033,
    "Uruguay": 0.0267,
    "Paraguay": 0.0244,
    "Argelia": 0.0218,
    "Irán": 0.0205
   }
  },
  "R32-9": {
   "in": {
    "Francia": 0.8391,
    "Croacia": 0.5617,
    "Ghana": 0.2266,
    "Inglaterra": 0.2117,
    "Noruega": 0.1609
   },
   "advance": {
    "Francia": 0.6371,
    "Croacia": 0.1575,
    "Inglaterra": 0.1018,
    "Noruega": 0.0848,
    "Ghana": 0.0188
   }
  },
  "R32-10": {
   "in": {
    "Estados Unidos": 0.9768,
    "Corea del Sur": 0.2771,
    "Senegal": 0.1436,
    "Suecia": 0.1006,
    "Australia": 0.0782,
    "Turquía": 0.0643,
    "Austria": 0.0546,
    "Irán": 0.0406
   },
   "advance": {
    "Estados Unidos": 0.4954,
    "Corea del Sur": 0.13,
    "Senegal": 0.0892,
    "Turquía": 0.0411,
    "Suecia": 0.04,
    "Australia": 0.0339,
    "Austria": 0.0313,
    "Uruguay": 0.0291
   }
  },
  "R32-11": {
   "in": {
    "Argentina": 0.9979,
    "Portugal": 0.5507,
    "Colombia": 0.4459,
    "RD Congo": 0.0034,
    "Austria": 0.0021
   },
   "advance": {
    "Argentina": 0.7004,
    "Portugal": 0.1748,
    "Colombia": 0.1238,
    "Austria": 0.0006,
    "RD Congo": 0.0004
   }
  },
  "R32-12": {
   "in": {
    "Países Bajos": 0.7514,
    "Corea del Sur": 0.2315,
    "Japón": 0.1939,
    "Suecia": 0.1713,
    "Senegal": 0.143,
    "Escocia": 0.126,
    "Australia": 0.0745,
    "Austria": 0.0682
   },
   "advance": {
    "Países Bajos": 0.5557,
    "Japón": 0.1302,
    "Corea del Sur": 0.065,
    "Senegal": 0.0562,
    "Suecia": 0.0454,
    "Turquía": 0.0266,
    "Austria": 0.0247,
    "Escocia": 0.0231
   }
  },
  "R32-13": {
   "in": {
    "Austria": 0.7007,
    "Colombia": 0.5541,
    "Portugal": 0.4459,
    "Argelia": 0.2972,
    "Argentina": 0.0021
   },
   "advance": {
    "Colombia": 0.3946,
    "Portugal": 0.3411,
    "Austria": 0.1971,
    "Argelia": 0.0656,
    "Argentina": 0.0016
   }
  },
  "R32-14": {
   "in": {
    "España": 0.8572,
    "Escocia": 0.2524,
    "Corea del Sur": 0.1287,
    "Uruguay": 0.1231,
    "Suecia": 0.1115,
    "Senegal": 0.1052,
    "Argelia": 0.092,
    "Austria": 0.06
   },
   "advance": {
    "España": 0.7673,
    "Uruguay": 0.0833,
    "Escocia": 0.0254,
    "Senegal": 0.0213,
    "Corea del Sur": 0.0209,
    "Suecia": 0.0139,
    "Argelia": 0.0118,
    "Austria": 0.011
   }
  },
  "R32-15": {
   "in": {
    "Noruega": 0.8391,
    "Inglaterra": 0.7864,
    "Croacia": 0.1797,
    "Francia": 0.1609,
    "Ghana": 0.0339
   },
   "advance": {
    "Inglaterra": 0.5277,
    "Noruega": 0.2889,
    "Francia": 0.0969,
    "Croacia": 0.0821,
    "Ghana": 0.0044
   }
  },
  "R16-0": {
   "in": {
    "Canadá": 0.8333,
    "México": 0.7024,
    "Sudáfrica": 0.1667,
    "Ecuador": 0.0617,
    "RD Congo": 0.0426,
    "Egipto": 0.0405,
    "Japón": 0.0393,
    "España": 0.0386
   },
   "advance": {
    "México": 0.4664,
    "Canadá": 0.3538,
    "Ecuador": 0.0384,
    "España": 0.0324,
    "Sudáfrica": 0.0251,
    "Japón": 0.025,
    "Egipto": 0.016,
    "RD Congo": 0.0137
   }
  },
  "R16-1": {
   "in": {
    "Brasil": 0.8607,
    "Marruecos": 0.6366,
    "Paraguay": 0.1908,
    "Australia": 0.1665,
    "Bosnia": 0.0326,
    "Ecuador": 0.0205,
    "Ghana": 0.0197,
    "Croacia": 0.0173
   },
   "advance": {
    "Brasil": 0.6636,
    "Marruecos": 0.1992,
    "Paraguay": 0.0509,
    "Australia": 0.0305,
    "Ecuador": 0.0127,
    "Croacia": 0.0111,
    "Bosnia": 0.0072,
    "Japón": 0.0063
   }
  },
  "R16-2": {
   "in": {
    "Alemania": 0.8165,
    "Japón": 0.4033,
    "Costa de Marfil": 0.2702,
    "Países Bajos": 0.1922,
    "Suecia": 0.1088,
    "Bosnia": 0.0414,
    "Ecuador": 0.0373,
    "Ghana": 0.0228
   },
   "advance": {
    "Alemania": 0.5575,
    "Japón": 0.1708,
    "Países Bajos": 0.1012,
    "Costa de Marfil": 0.0627,
    "Suecia": 0.0273,
    "Ecuador": 0.0176,
    "Croacia": 0.0124,
    "Bosnia": 0.0096
   }
  },
  "R16-3": {
   "in": {
    "Bélgica": 0.6414,
    "Egipto": 0.3551,
    "Irán": 0.2755,
    "Cabo Verde": 0.1173,
    "España": 0.0806,
    "Arabia Saudita": 0.0748,
    "Uruguay": 0.0666,
    "Senegal": 0.0539
   },
   "advance": {
    "Bélgica": 0.4608,
    "Egipto": 0.1167,
    "Irán": 0.1004,
    "España": 0.0689,
    "Uruguay": 0.0442,
    "Senegal": 0.0286,
    "Cabo Verde": 0.0268,
    "Paraguay": 0.0238
   }
  },
  "R16-4": {
   "in": {
    "Francia": 0.6371,
    "Suiza": 0.6299,
    "Croacia": 0.1643,
    "Inglaterra": 0.1018,
    "Noruega": 0.0848,
    "Corea del Sur": 0.0684,
    "Senegal": 0.0656,
    "Turquía": 0.033
   },
   "advance": {
    "Francia": 0.5138,
    "Suiza": 0.1771,
    "Croacia": 0.0918,
    "Inglaterra": 0.076,
    "Noruega": 0.0519,
    "Senegal": 0.0174,
    "Corea del Sur": 0.0146,
    "Uruguay": 0.0107
   }
  },
  "R16-5": {
   "in": {
    "Argentina": 0.7004,
    "Estados Unidos": 0.4954,
    "Portugal": 0.1748,
    "Corea del Sur": 0.13,
    "Colombia": 0.1238,
    "Senegal": 0.0892,
    "Turquía": 0.0411,
    "Suecia": 0.04
   },
   "advance": {
    "Argentina": 0.6068,
    "Portugal": 0.1349,
    "Colombia": 0.0907,
    "Estados Unidos": 0.0761,
    "Corea del Sur": 0.0196,
    "Senegal": 0.0184,
    "Turquía": 0.0096,
    "Uruguay": 0.0083
   }
  },
  "R16-6": {
   "in": {
    "Países Bajos": 0.5557,
    "Colombia": 0.3946,
    "Portugal": 0.3411,
    "Austria": 0.2218,
    "Japón": 0.1302,
    "Argelia": 0.0758,
    "Corea del Sur": 0.065,
    "Senegal": 0.0562
   },
   "advance": {
    "Países Bajos": 0.2966,
    "Colombia": 0.2302,
    "Portugal": 0.2179,
    "Austria": 0.0862,
    "Japón": 0.0548,
    "Argelia": 0.0237,
    "Senegal": 0.0229,
    "Corea del Sur": 0.0191
   }
  },
  "R16-7": {
   "in": {
    "España": 0.7673,
    "Inglaterra": 0.5277,
    "Noruega": 0.2889,
    "Francia": 0.0969,
    "Croacia": 0.0876,
    "Uruguay": 0.0833,
    "Escocia": 0.0254,
    "Senegal": 0.0213
   },
   "advance": {
    "España": 0.5381,
    "Inglaterra": 0.2394,
    "Noruega": 0.0806,
    "Francia": 0.0469,
    "Uruguay": 0.0341,
    "Croacia": 0.0261,
    "Senegal": 0.008,
    "Corea del Sur": 0.0043
   }
  },
  "QF-0": {
   "in": {
    "Brasil": 0.6636,
    "México": 0.4664,
    "Canadá": 0.3538,
    "Marruecos": 0.1992,
    "Ecuador": 0.0511,
    "Paraguay": 0.0509,
    "España": 0.0335,
    "Japón": 0.0313
   },
   "advance": {
    "Brasil": 0.4836,
    "México": 0.1862,
    "Canadá": 0.1093,
    "Marruecos": 0.1004,
    "España": 0.024,
    "Ecuador": 0.0231,
    "Paraguay": 0.0214,
    "Japón": 0.0149
   }
  },
  "QF-1": {
   "in": {
    "Alemania": 0.5575,
    "Bélgica": 0.4638,
    "Japón": 0.1752,
    "Egipto": 0.1191,
    "Irán": 0.1022,
    "Países Bajos": 0.1012,
    "España": 0.0689,
    "Costa de Marfil": 0.0638
   },
   "advance": {
    "Alemania": 0.3671,
    "Bélgica": 0.2134,
    "Japón": 0.0985,
    "Países Bajos": 0.0658,
    "España": 0.0534,
    "Egipto": 0.0304,
    "Irán": 0.0257,
    "Uruguay": 0.023
   }
  },
  "QF-2": {
   "in": {
    "Argentina": 0.6068,
    "Francia": 0.5138,
    "Suiza": 0.1771,
    "Portugal": 0.1349,
    "Croacia": 0.094,
    "Colombia": 0.0907,
    "Estados Unidos": 0.0761,
    "Inglaterra": 0.076
   },
   "advance": {
    "Argentina": 0.4029,
    "Francia": 0.2902,
    "Portugal": 0.0689,
    "Suiza": 0.0487,
    "Inglaterra": 0.0408,
    "Colombia": 0.0407,
    "Croacia": 0.0284,
    "Estados Unidos": 0.0187
   }
  },
  "QF-3": {
   "in": {
    "España": 0.5381,
    "Países Bajos": 0.2966,
    "Inglaterra": 0.2394,
    "Colombia": 0.2302,
    "Portugal": 0.2179,
    "Austria": 0.0894,
    "Noruega": 0.0806,
    "Japón": 0.055
   },
   "advance": {
    "España": 0.4133,
    "Inglaterra": 0.1587,
    "Países Bajos": 0.0995,
    "Portugal": 0.0843,
    "Colombia": 0.0767,
    "Francia": 0.0344,
    "Noruega": 0.0342,
    "Austria": 0.0203
   }
  },
  "SF-0": {
   "in": {
    "Brasil": 0.4836,
    "Alemania": 0.3671,
    "Bélgica": 0.2135,
    "México": 0.1862,
    "Japón": 0.1134,
    "Canadá": 0.1093,
    "Marruecos": 0.1004,
    "España": 0.0774
   },
   "advance": {
    "Brasil": 0.3208,
    "Alemania": 0.1902,
    "Bélgica": 0.094,
    "México": 0.0854,
    "España": 0.0588,
    "Japón": 0.0463,
    "Canadá": 0.0417,
    "Marruecos": 0.0384
   }
  },
  "SF-1": {
   "in": {
    "España": 0.4133,
    "Argentina": 0.4035,
    "Francia": 0.3246,
    "Inglaterra": 0.1995,
    "Portugal": 0.1532,
    "Colombia": 0.1174,
    "Países Bajos": 0.0995,
    "Noruega": 0.0493
   },
   "advance": {
    "España": 0.2623,
    "Argentina": 0.2433,
    "Francia": 0.1855,
    "Inglaterra": 0.0912,
    "Portugal": 0.0655,
    "Colombia": 0.0393,
    "Países Bajos": 0.0369,
    "Noruega": 0.0135
   }
  },
  "F-0": {
   "in": {
    "España": 0.3211,
    "Brasil": 0.3208,
    "Argentina": 0.2433,
    "Alemania": 0.1902,
    "Francia": 0.1855,
    "Bélgica": 0.0949,
    "Inglaterra": 0.0915,
    "México": 0.0854
   },
   "advance": {
    "España": 0.2402,
    "Argentina": 0.1731,
    "Brasil": 0.1313,
    "Francia": 0.1278,
    "Alemania": 0.0652,
    "Inglaterra": 0.0554,
    "Portugal": 0.0382,
    "Países Bajos": 0.0304
   }
  }
 }
}